[
  {
    "coherence": 0.002824512246475397,
    "entropy": 0.9971754877535246,
    "hazard": 0.5078226857887875,
    "line_number": 1,
    "occurrences": 1,
    "patternability": 0.49217731421121247,
    "rupture": 0.5078226857887875,
    "search_text": "docs/auth.md doc docs/auth.md\ndoc\n# Auth\nChanging auth or session handling impacts token refresh and rollback flows.",
    "signature": "c0.0_s0.49_e1.0",
    "source": "docs/auth.md",
    "source_type": "doc",
    "span_id": "1c575e30ef159e84468f6f2ff8ce02a5",
    "stability": 0.4921773142112125,
    "text": "docs/auth.md\ndoc\n# Auth\nChanging auth or session handling impacts token refresh and rollback flows."
  },
  {
    "coherence": 0.04556599707503495,
    "entropy": 0.954434002924965,
    "hazard": 0.5106382978723404,
    "line_number": 1,
    "occurrences": 1,
    "patternability": 0.4893617021276596,
    "rupture": 0.5106382978723404,
    "search_text": "docs/auth.md doc # Auth",
    "signature": "c0.05_s0.49_e0.95",
    "source": "docs/auth.md",
    "source_type": "doc",
    "span_id": "ff20ab3797413ded17bf0542b8650158",
    "stability": 0.4893617021276596,
    "text": "# Auth"
  },
  {
    "coherence": 0.0013549545805056074,
    "entropy": 0.9986450454194944,
    "hazard": 0.5041736227045075,
    "line_number": 3,
    "occurrences": 1,
    "patternability": 0.4958263772954925,
    "rupture": 0.5041736227045075,
    "search_text": "docs/auth.md doc Changing auth or session handling impacts token refresh and rollback flows.",
    "signature": "c0.0_s0.5_e1.0",
    "source": "docs/auth.md",
    "source_type": "doc",
    "span_id": "8dd7a0579c62c576d6014b53035f47b4",
    "stability": 0.4958263772954925,
    "text": "Changing auth or session handling impacts token refresh and rollback flows."
  },
  {
    "coherence": 0.006166323209648494,
    "entropy": 0.9938336767903515,
    "hazard": 0.508843537414966,
    "line_number": 1,
    "occurrences": 1,
    "patternability": 0.491156462585034,
    "rupture": 0.508843537414966,
    "search_text": "prs/pr_1842.md pr prs/pr_1842.md\npr\n# PR 1842\nAdjusted token refresh behavior during the auth session rollout.",
    "signature": "c0.01_s0.49_e0.99",
    "source": "prs/pr_1842.md",
    "source_type": "pr",
    "span_id": "0e53fe93d4bf508012ff53422e02d718",
    "stability": 0.491156462585034,
    "text": "prs/pr_1842.md\npr\n# PR 1842\nAdjusted token refresh behavior during the auth session rollout."
  },
  {
    "coherence": 0.1120236804848651,
    "entropy": 0.8879763195151349,
    "hazard": 0.4507042253521127,
    "line_number": 1,
    "occurrences": 1,
    "patternability": 0.5492957746478873,
    "rupture": 0.4507042253521127,
    "search_text": "prs/pr_1842.md pr # PR 1842",
    "signature": "c0.11_s0.55_e0.89",
    "source": "prs/pr_1842.md",
    "source_type": "pr",
    "span_id": "e7174d8c8e91c2e1ba4674f4066498b7",
    "stability": 0.5492957746478873,
    "text": "# PR 1842"
  },
  {
    "coherence": 0.0013322437816536414,
    "entropy": 0.9986677562183464,
    "hazard": 0.5322896281800391,
    "line_number": 3,
    "occurrences": 1,
    "patternability": 0.4677103718199609,
    "rupture": 0.5322896281800391,
    "search_text": "prs/pr_1842.md pr Adjusted token refresh behavior during the auth session rollout.",
    "signature": "c0.0_s0.47_e1.0",
    "source": "prs/pr_1842.md",
    "source_type": "pr",
    "span_id": "078268545d4ac804cc8c78e10fa7e90f",
    "stability": 0.4677103718199609,
    "text": "Adjusted token refresh behavior during the auth session rollout."
  },
  {
    "coherence": 0.0006483650351674086,
    "entropy": 0.9993516349648326,
    "hazard": 0.5371577574967406,
    "line_number": 1,
    "occurrences": 1,
    "patternability": 0.46284224250325945,
    "rupture": 0.5371577574967406,
    "search_text": "runbooks/session_rollback.md runbook runbooks/session_rollback.md\nrunbook\n# Session Rollback\nIf token refresh fails, use the session rollback procedure.",
    "signature": "c0.0_s0.46_e1.0",
    "source": "runbooks/session_rollback.md",
    "source_type": "runbook",
    "span_id": "fe217128887ca1ab0c7e83333513a437",
    "stability": 0.4628422425032595,
    "text": "runbooks/session_rollback.md\nrunbook\n# Session Rollback\nIf token refresh fails, use the session rollback procedure."
  },
  {
    "coherence": 0.0005566669097010202,
    "entropy": 0.999443333090299,
    "hazard": 0.5384615384615384,
    "line_number": 1,
    "occurrences": 1,
    "patternability": 0.46153846153846156,
    "rupture": 0.5384615384615384,
    "search_text": "runbooks/session_rollback.md runbook # Session Rollback",
    "signature": "c0.0_s0.46_e1.0",
    "source": "runbooks/session_rollback.md",
    "source_type": "runbook",
    "span_id": "72a7a170ddf412374995c37d4af7320e",
    "stability": 0.46153846153846156,
    "text": "# Session Rollback"
  },
  {
    "coherence": 0.0021899141279471124,
    "entropy": 0.9978100858720529,
    "hazard": 0.5265392781316348,
    "line_number": 3,
    "occurrences": 1,
    "patternability": 0.4734607218683652,
    "rupture": 0.5265392781316348,
    "search_text": "runbooks/session_rollback.md runbook If token refresh fails, use the session rollback procedure.",
    "signature": "c0.0_s0.47_e1.0",
    "source": "runbooks/session_rollback.md",
    "source_type": "runbook",
    "span_id": "f55ae613c275c82116d6d11c4079c9cb",
    "stability": 0.4734607218683652,
    "text": "If token refresh fails, use the session rollback procedure."
  },
  {
    "coherence": 0.00016900200960212608,
    "entropy": 0.9998309979903979,
    "hazard": 0.5396419437340153,
    "line_number": 1,
    "occurrences": 1,
    "patternability": 0.4603580562659847,
    "rupture": 0.5396419437340153,
    "search_text": "src/auth.py code src/auth.py\ncode\ndef refresh_token():\nreturn 'ok'",
    "signature": "c0.0_s0.46_e1.0",
    "source": "src/auth.py",
    "source_type": "code",
    "span_id": "9549de65747dcb1f4b28a8cd4e46f479",
    "stability": 0.4603580562659847,
    "text": "src/auth.py\ncode\ndef refresh_token():\nreturn 'ok'"
  },
  {
    "coherence": 0.005887049868074534,
    "entropy": 0.9941129501319255,
    "hazard": 0.519163763066202,
    "line_number": 1,
    "occurrences": 1,
    "patternability": 0.48083623693379796,
    "rupture": 0.519163763066202,
    "search_text": "src/auth.py code def refresh_token():\n    return 'ok'",
    "signature": "c0.01_s0.48_e0.99",
    "source": "src/auth.py",
    "source_type": "code",
    "span_id": "5b49520fc8bca82e35ad6f0376cbcb47",
    "stability": 0.48083623693379796,
    "text": "def refresh_token():\n    return 'ok'"
  },
  {
    "coherence": 0.00025929327156576365,
    "entropy": 0.9997407067284343,
    "hazard": 0.5404172099087353,
    "line_number": 1,
    "occurrences": 1,
    "patternability": 0.4595827900912647,
    "rupture": 0.5404172099087353,
    "search_text": "src/session.py code src/session.py\ncode\nfrom src.auth import refresh_token\ndef session_guard():\nreturn refresh_token()",
    "signature": "c0.0_s0.46_e1.0",
    "source": "src/session.py",
    "source_type": "code",
    "span_id": "217944420a031ead89cdd75a91c881c0",
    "stability": 0.4595827900912647,
    "text": "src/session.py\ncode\nfrom src.auth import refresh_token\ndef session_guard():\nreturn refresh_token()"
  },
  {
    "coherence": 0.00015600638469315253,
    "entropy": 0.9998439936153068,
    "hazard": 0.5313653136531366,
    "line_number": 1,
    "occurrences": 1,
    "patternability": 0.46863468634686345,
    "rupture": 0.5313653136531366,
    "search_text": "src/session.py code from src.auth import refresh_token",
    "signature": "c0.0_s0.47_e1.0",
    "source": "src/session.py",
    "source_type": "code",
    "span_id": "f768bc2c51792873f37b36058ab89b02",
    "stability": 0.46863468634686345,
    "text": "from src.auth import refresh_token"
  },
  {
    "coherence": 0.0024709404842686578,
    "entropy": 0.9975290595157313,
    "hazard": 0.5306666666666666,
    "line_number": 3,
    "occurrences": 1,
    "patternability": 0.4693333333333334,
    "rupture": 0.5306666666666666,
    "search_text": "src/session.py code def session_guard():\n    return refresh_token()",
    "signature": "c0.0_s0.47_e1.0",
    "source": "src/session.py",
    "source_type": "code",
    "span_id": "b406703943fe5fa202b5748ad3a230e1",
    "stability": 0.4693333333333334,
    "text": "def session_guard():\n    return refresh_token()"
  },
  {
    "coherence": 0.0006482813422424849,
    "entropy": 0.9993517186577575,
    "hazard": 0.530638852672751,
    "line_number": 1,
    "occurrences": 1,
    "patternability": 0.469361147327249,
    "rupture": 0.530638852672751,
    "search_text": "tests/test_auth.py test tests/test_auth.py\ntest\nfrom src.session import session_guard\ndef test_session_guard():\nassert session_guard() == 'ok'",
    "signature": "c0.0_s0.47_e1.0",
    "source": "tests/test_auth.py",
    "source_type": "test",
    "span_id": "68ac3c49e260b0d3c973389f97eae055",
    "stability": 0.469361147327249,
    "text": "tests/test_auth.py\ntest\nfrom src.session import session_guard\ndef test_session_guard():\nassert session_guard() == 'ok'"
  },
  {
    "coherence": 0.003988476451471268,
    "entropy": 0.9960115235485287,
    "hazard": 0.5288135593220339,
    "line_number": 1,
    "occurrences": 1,
    "patternability": 0.4711864406779661,
    "rupture": 0.5288135593220339,
    "search_text": "tests/test_auth.py test from src.session import session_guard",
    "signature": "c0.0_s0.47_e1.0",
    "source": "tests/test_auth.py",
    "source_type": "test",
    "span_id": "02eb1b4366c32bfcdfbccb5b73aa95e2",
    "stability": 0.4711864406779661,
    "text": "from src.session import session_guard"
  },
  {
    "coherence": 0.0008016457363602125,
    "entropy": 0.9991983542636398,
    "hazard": 0.5156576200417536,
    "line_number": 3,
    "occurrences": 1,
    "patternability": 0.48434237995824636,
    "rupture": 0.5156576200417536,
    "search_text": "tests/test_auth.py test def test_session_guard():\n    assert session_guard() == 'ok'",
    "signature": "c0.0_s0.48_e1.0",
    "source": "tests/test_auth.py",
    "source_type": "test",
    "span_id": "2629a70323d24793318a7c8c308534c8",
    "stability": 0.48434237995824636,
    "text": "def test_session_guard():\n    assert session_guard() == 'ok'"
  }
]